LICENCE
gegca/__init__.py
gegca/operations.py
gegca/py.typed
gegca-0.1.3.dist-info/LICENCE
gegca-0.1.3.dist-info/METADATA
gegca-0.1.3.dist-info/WHEEL
gegca-0.1.3.dist-info/RECORD
