Metadata-Version: 2.1
Name: gegca
Version: 0.1.3
Summary: Global-mean climate assessment of global emissions scenarios.
License: BSD-3-Clause
Author: Zebedee Nicholls
Author-email: zebedee.nicholls@climate-energy-college.org
Requires-Python: >=3.9,<4.0
Classifier: License :: OSI Approved :: BSD License
Classifier: Programming Language :: Python :: 3
Classifier: Programming Language :: Python :: 3.9
Classifier: Programming Language :: Python :: 3.10
Classifier: Programming Language :: Python :: 3.11
Classifier: Programming Language :: Python :: 3.12
Provides-Extra: notebooks
Provides-Extra: plots
Requires-Dist: matplotlib ; extra == "plots"
Requires-Dist: notebook ; extra == "notebooks"
Requires-Dist: pandas
